template_project_nbdev/__init__.py
template_project_nbdev/_modidx.py
template_project_nbdev/inc_dec.py
template_project_nbdev/module/__init__.py
template_project_nbdev/module/submodule.py
template_project_nbdev-0.0.2.dist-info/LICENSE
template_project_nbdev-0.0.2.dist-info/METADATA
template_project_nbdev-0.0.2.dist-info/WHEEL
template_project_nbdev-0.0.2.dist-info/entry_points.txt
template_project_nbdev-0.0.2.dist-info/top_level.txt
template_project_nbdev-0.0.2.dist-info/RECORD
